expr/__init__.py
expr/ast.py
expr/builtin.py
expr/core.py
expr/errors.py
expr/grammar.py
expr/parser.py
expr/py.typed
expr/util.py
expr_py_inf-0.4.0.dist-info/METADATA
expr_py_inf-0.4.0.dist-info/WHEEL
expr_py_inf-0.4.0.dist-info/top_level.txt
expr_py_inf-0.4.0.dist-info/RECORD
