Metadata-Version: 2.4
Name: expr.py-inf
Version: 0.4.0
Summary: A safe and simple math expression evaluator for Python.
Home-page: https://github.com/TheMrRedSlime/expr.py-inf
Author: TheMrRedSlime
License: MIT
Project-URL: Issue tracker, https://github.com/TheMrRedSlime/expr.py-inf
Classifier: License :: OSI Approved :: MIT License
Classifier: Intended Audience :: Developers
Classifier: Natural Language :: English
Classifier: Operating System :: OS Independent
Classifier: Programming Language :: Python :: 3.8
Classifier: Programming Language :: Python :: 3.9
Classifier: Topic :: Software Development :: Libraries
Classifier: Topic :: Software Development :: Libraries :: Python Modules
Classifier: Topic :: Utilities
Classifier: Typing :: Typed
Requires-Python: >=3.8.0
Requires-Dist: rply>=0.7.8
Dynamic: author
Dynamic: classifier
Dynamic: description
Dynamic: description-content-type
Dynamic: home-page
Dynamic: license
Dynamic: project-url
Dynamic: requires-dist
Dynamic: requires-python
Dynamic: summary
